README.rst
setup.py
bin/btadiff
bin/btaimport
bin/btamanage
bin/btaminer
bta/__init__.py
bta/datatable.py
bta/dblog.py
bta/dbmeta.py
bta/diff.py
bta/docstruct.py
bta/manage.py
bta/miner.py
bta/normalization.py
bta/ntds2db.py
bta/postprocessing.py
bta/sd.py
bta.egg-info/PKG-INFO
bta.egg-info/SOURCES.txt
bta.egg-info/dependency_links.txt
bta.egg-info/requires.txt
bta.egg-info/top_level.txt
bta/backend/__init__.py
bta/backend/ldap_backend.py
bta/backend/mongo.py
bta/formatters/__init__.py
bta/formatters/csvzip.py
bta/formatters/excel.py
bta/formatters/raw.py
bta/formatters/rawzip.py
bta/formatters/rest.py
bta/miners/DN_grep.py
bta/miners/DN_tree.py
bta/miners/SD_prop.py
bta/miners/SD_users.py
bta/miners/SID_history.py
bta/miners/__init__.py
bta/miners/accounts.py
bta/miners/admin_count_check.py
bta/miners/audit_extended_rights.py
bta/miners/audit_full.py
bta/miners/audit_groups.py
bta/miners/audit_passwords.py
bta/miners/audit_schema.py
bta/miners/audit_sdprop.py
bta/miners/audit_uac.py
bta/miners/can_create.py
bta/miners/check_UAC.py
bta/miners/domains.py
bta/miners/info.py
bta/miners/list_ACE.py
bta/miners/list_group.py
bta/miners/list_links.py
bta/miners/list_objects.py
bta/miners/map_links.py
bta/miners/membership.py
bta/miners/new_admin.py
bta/miners/password_policy.py
bta/miners/passwords.py
bta/miners/schema.py
bta/miners/schema_modifs.py
bta/miners/search_for_right.py
bta/miners/trust_link.py
bta/miners/who_is.py
bta/tools/RPNedit.py
bta/tools/WellKnownSID.py
bta/tools/__init__.py
bta/tools/ask.py
bta/tools/decoding.py
bta/tools/expr.py
bta/tools/flags.py
bta/tools/importer.py
bta/tools/mtools.py
bta/tools/progressbar.py
bta/tools/registry.py
libesedb/__init__.py
libesedb/esetypes.py
libesedb/libesedb.py
test/test_dbmeta.py
test/test_docstruct.py
test/test_expr.py
test/test_ldapreqbuilder.py
test/test_miner_check_UAC.py
test/test_miner_info.py
test/test_miners.py
test/test_mongobackend.py
test/test_mongoreqbuilder.py