Metadata-Version: 1.0
Name: bta
Version: 0.6
Summary: Active Directory Auditing tool
Home-page: UNKNOWN
Author: Philippe Biondi
Author-email: phil@secdev.org
License: UNKNOWN
Platform: UNKNOWN
